mattermost_messenger/__init__.py
mattermost_messenger/__main__.py
mattermost_messenger/handler.py
mattermost_messenger/py.typed
mattermost_messenger/sender.py
mattermost_messenger/threaded.py
mattermost_messenger-1.0.1.dist-info/LICENSE.md
mattermost_messenger-1.0.1.dist-info/METADATA
mattermost_messenger-1.0.1.dist-info/WHEEL
mattermost_messenger-1.0.1.dist-info/entry_points.txt
mattermost_messenger-1.0.1.dist-info/RECORD
