Metadata-Version: 2.1
Name: mattermost-messenger
Version: 1.0.1
Summary: Several classes and tools to send messages to a Mattermost channel
License: BSD-3-Clause
Author: Björn Hendriks
Author-email: bjoern.hendriks@dlr.de
Requires-Python: >=3.10,<4.0
Classifier: License :: OSI Approved :: BSD License
Classifier: Programming Language :: Python :: 3
Classifier: Programming Language :: Python :: 3.10
Classifier: Programming Language :: Python :: 3.11
Project-URL: Changelog, https://github.com/DLR-TS/mattermost-messenger/blob/main/CHANGELOG.md
Project-URL: Issues, https://github.com/DLR-TS/mattermost-messenger/issues
Project-URL: Repository, https://github.com/DLR-TS/mattermost-messenger
